get_locator/__init__.py
get_locator/create_setup.py
get_locator/inspector.py
get_locator/locators.py
get_locator/run_inspector.py
get_locator/run_text.txt
get_locator/utils.py
get_locator-10.1.2.dist-info/METADATA
get_locator-10.1.2.dist-info/WHEEL
get_locator-10.1.2.dist-info/entry_points.txt
get_locator-10.1.2.dist-info/top_level.txt
get_locator-10.1.2.dist-info/RECORD
