Metadata-Version: 2.2
Name: get-locator
Version: 10.1.2
Summary: Pytest plugin. Run command, e.g.: run-inspector --url "https://demoqa.com/automation-practice-form"
Author-email: Yevhen Halitsyn <galitsyn.evgeniy955@gmail.com>
License: MIT
Classifier: Programming Language :: Python :: 3
Classifier: License :: OSI Approved :: MIT License
Classifier: Operating System :: OS Independent
Requires-Python: >=3.9
Requires-Dist: selenium
Requires-Dist: pyperclip
Requires-Dist: pynput
